ipyvue_async/__init__.py
ipyvue_async/channel.py
ipyvue_async/comm_widget.py
ipyvue_async/force_load.py
ipyvue_async/labextension/package.json
ipyvue_async/labextension/static/261.17f7abbb72e78f743ed2.js
ipyvue_async/labextension/static/261.a4594250659e8db5d435.js
ipyvue_async/labextension/static/568.6c5b39396739f5357389.js
ipyvue_async/labextension/static/568.84260b5760da3e416c30.js
ipyvue_async/labextension/static/remoteEntry.083505931bc1604d1a78.js
ipyvue_async/labextension/static/remoteEntry.90634c7827e3115ca946.js
ipyvue_async/labextension/static/style.js
ipyvue_async/nbextension/extension.js
ipyvue_async/nbextension/index.js
ipyvue_async-0.1.1.data/data/etc/jupyter/nbconfig/notebook.d/ipyvue-async.json
ipyvue_async-0.1.1.data/data/share/jupyter/labextensions/ipyvue-async/install.json
ipyvue_async-0.1.1.data/data/share/jupyter/labextensions/ipyvue-async/package.json
ipyvue_async-0.1.1.data/data/share/jupyter/labextensions/ipyvue-async/static/261.a4594250659e8db5d435.js
ipyvue_async-0.1.1.data/data/share/jupyter/labextensions/ipyvue-async/static/568.6c5b39396739f5357389.js
ipyvue_async-0.1.1.data/data/share/jupyter/labextensions/ipyvue-async/static/remoteEntry.083505931bc1604d1a78.js
ipyvue_async-0.1.1.data/data/share/jupyter/labextensions/ipyvue-async/static/style.js
ipyvue_async-0.1.1.data/data/share/jupyter/nbextensions/ipyvue-async/extension.js
ipyvue_async-0.1.1.data/data/share/jupyter/nbextensions/ipyvue-async/extension.js.map
ipyvue_async-0.1.1.data/data/share/jupyter/nbextensions/ipyvue-async/index.js
ipyvue_async-0.1.1.data/data/share/jupyter/nbextensions/ipyvue-async/index.js.map
ipyvue_async-0.1.1.dist-info/LICENSE
ipyvue_async-0.1.1.dist-info/METADATA
ipyvue_async-0.1.1.dist-info/WHEEL
ipyvue_async-0.1.1.dist-info/top_level.txt
ipyvue_async-0.1.1.dist-info/RECORD
