Metadata-Version: 2.1
Name: ipyvue-async
Version: 0.1.1
Summary: Asynchronous communication channels between Vue components in Jupyter and Python
Home-page: https://github.com/flatsurf/ipyvue-async
Author: Julian Rüth
Author-email: julian.rueth@fsfe.org
License: UNKNOWN
Keywords: ipython,jupyter,widgets
Platform: UNKNOWN
Classifier: Development Status :: 4 - Beta
Classifier: Framework :: IPython
Classifier: License :: OSI Approved :: MIT License
Classifier: Intended Audience :: Developers
Classifier: Programming Language :: Python :: 3.6
Classifier: Programming Language :: Python :: 3.7
Classifier: Programming Language :: Python :: 3.8
Classifier: Programming Language :: Python :: 3.9
License-File: LICENSE
